snowcli_tools/__init__.py
snowcli_tools/catalog/__init__.py
snowcli_tools/catalog/models.py
snowcli_tools/catalog/service.py
snowcli_tools/circuit_breaker.py
snowcli_tools/cli.py
snowcli_tools/commands/__init__.py
snowcli_tools/commands/analyze.py
snowcli_tools/commands/discover.py
snowcli_tools/commands/query.py
snowcli_tools/commands/registry.py
snowcli_tools/commands/setup.py
snowcli_tools/commands/utils.py
snowcli_tools/config.py
snowcli_tools/context.py
snowcli_tools/dependency/__init__.py
snowcli_tools/dependency/models.py
snowcli_tools/dependency/service.py
snowcli_tools/error_handling.py
snowcli_tools/errors/__init__.py
snowcli_tools/errors/formatter.py
snowcli_tools/lineage/__init__.py
snowcli_tools/lineage/audit.py
snowcli_tools/lineage/base.py
snowcli_tools/lineage/builder.py
snowcli_tools/lineage/column_parser.py
snowcli_tools/lineage/constants.py
snowcli_tools/lineage/cross_db.py
snowcli_tools/lineage/exceptions.py
snowcli_tools/lineage/external.py
snowcli_tools/lineage/factory.py
snowcli_tools/lineage/graph.py
snowcli_tools/lineage/history.py
snowcli_tools/lineage/identifiers.py
snowcli_tools/lineage/impact.py
snowcli_tools/lineage/loader.py
snowcli_tools/lineage/logging_config.py
snowcli_tools/lineage/queries.py
snowcli_tools/lineage/sql_parser.py
snowcli_tools/lineage/transformations.py
snowcli_tools/lineage/types.py
snowcli_tools/lineage/utils.py
snowcli_tools/logging/__init__.py
snowcli_tools/logging/structured.py
snowcli_tools/mcp/__init__.py
snowcli_tools/mcp/tools/__init__.py
snowcli_tools/mcp/tools/base.py
snowcli_tools/mcp/tools/build_catalog.py
snowcli_tools/mcp/tools/build_dependency_graph.py
snowcli_tools/mcp/tools/check_profile_config.py
snowcli_tools/mcp/tools/check_resource_dependencies.py
snowcli_tools/mcp/tools/execute_query.py
snowcli_tools/mcp/tools/get_catalog_summary.py
snowcli_tools/mcp/tools/get_resource_status.py
snowcli_tools/mcp/tools/health_check.py
snowcli_tools/mcp/tools/preview_table.py
snowcli_tools-1.8.0.dist-info/WHEEL
snowcli_tools-1.8.0.dist-info/entry_points.txt
snowcli_tools-1.8.0.dist-info/METADATA
snowcli_tools-1.8.0.dist-info/RECORD
