Metadata-Version: 2.3
Name: snowcli-tools
Version: 1.8.0
Summary: Snowflake CLI Tools: generate a Data Catalog and Dependency Graph on top of the official Snowflake CLI; includes parallel query helpers, advanced lineage features, SQL safety validation, and agent-first error handling
Author: Evan Kim
Author-email: Evan Kim <ekcopersonal@gmail.com>
Requires-Dist: click>=8.0.0
Requires-Dist: rich>=13.0.0
Requires-Dist: pyyaml>=6.0.0
Requires-Dist: snowflake-cli>=2.0.0
Requires-Dist: sqlglot>=27.16.3
Requires-Dist: pyvis>=0.3.2
Requires-Dist: networkx>=3.0
Requires-Dist: websockets>=15.0.1
Requires-Dist: mcp>=1.0.0
Requires-Dist: fastmcp>=2.8.1
Requires-Dist: snowflake-labs-mcp>=1.3.3
Requires-Dist: pydantic>=2.7.0
Requires-Dist: mcp>=1.0.0 ; extra == 'mcp'
Requires-Dist: fastmcp>=2.8.1 ; extra == 'mcp'
Requires-Dist: snowflake-labs-mcp>=1.3.3 ; extra == 'mcp'
Requires-Python: >=3.12
Project-URL: Documentation, https://github.com/Evan-Kim2028/snowcli-tools#readme
Project-URL: Homepage, https://github.com/Evan-Kim2028/snowcli-tools
Project-URL: Repository, https://github.com/Evan-Kim2028/snowcli-tools
Provides-Extra: mcp
